HowdenRag/__init__.py
HowdenRag/handler_create_index.py
HowdenRag/handler_embed.py
HowdenRag/rag.py
HowdenRag/rerank/valg_af_reranker.md
HowdenRag/src/answer_generation.py
HowdenRag/src/chroma_storage.py
HowdenRag/src/chunking.py
HowdenRag/src/clients/__init__.py
HowdenRag/src/clients/azure_client.py
HowdenRag/src/clients/base_client.py
HowdenRag/src/clients/openai_client.py
HowdenRag/src/config_model.py
HowdenRag/src/determine_date.py
HowdenRag/src/logging.py
HowdenRag/src/main.py
HowdenRag/src/parser.py
HowdenRag/src/rerank.py
HowdenRag/src/services/llm_service.py
HowdenRag/src/split_document.py
HowdenRag/utils.py
howden_rag-0.1.2.dist-info/METADATA
howden_rag-0.1.2.dist-info/WHEEL
howden_rag-0.1.2.dist-info/RECORD
