Metadata-Version: 2.3
Name: howden-rag
Version: 0.1.2
Summary: Package that handles rag functionalitet.
License: MIT
Keywords: config,configuration,pydantic,json
Author: JesperThoftIllemannJ
Author-email: jesper.jaeger@howdendanmark.dk
Requires-Python: >=3.12,<3.14
Classifier: License :: OSI Approved :: MIT License
Classifier: Programming Language :: Python :: 3
Classifier: Programming Language :: Python :: 3.12
Classifier: Programming Language :: Python :: 3.13
Requires-Dist: azure-identity (>=1.25.0,<2.0.0)
Requires-Dist: azure-search-documents (>=11.5.3,<12.0.0)
Requires-Dist: howdenconfig (>=1.0.6,<2.0.0)
Requires-Dist: llama-index-core (>=0.14.3,<0.15.0)
Requires-Dist: openai (>=1.109.1,<2.0.0)
Requires-Dist: pathlib (>=1.0.1,<2.0.0)
Requires-Dist: python-dotenv (>=1.1.1,<2.0.0)
Project-URL: Documentation, https://github.com/yourusername/config
Project-URL: Homepage, https://github.com/yourusername/config
Project-URL: Repository, https://github.com/yourusername/config
